{
  "ApplicationConfiguration": {
    "Network": "testnet",
    "AddressVersion": 53,
    "Storage": {
      "Engine": "rocksdb",
      "Path": "./neo-data/chain-testnet",
      "Options": {
        "WriteBufferSize": 67108864,
        "MaxOpenFiles": 1000,
        "BlockCacheSize": 134217728,
        "CompressionEnabled": true
      }
    },
    "P2P": {
      "Port": 20333,
      "MaxConnections": 100,
      "MinDesiredConnections": 10,
      "MaxConnectionsPerAddress": 3,
      "SeedList": [
        "seed1t.neo.org:20333",
        "seed2t.neo.org:20333",
        "seed3t.neo.org:20333",
        "seed4t.neo.org:20333",
        "seed5t.neo.org:20333"
      ]
    },
    "RPC": {
      "Enabled": true,
      "Port": 20334,
      "SslEnabled": false,
      "MaxConcurrentConnections": 40,
      "MaxIteratorResultItems": 100,
      "MaxFindResultItems": 100,
      "MaxGasInvoke": 100000000,
      "EnableCorsAllowOrigin": false
    },
    "UnlockWallet": {
      "Path": "",
      "Password": "",
      "IsActive": false
    },
    "Logging": {
      "Level": "info",
      "Path": "./logs",
      "ConsoleEnabled": true,
      "FileEnabled": true,
      "MaxFileSize": 10485760,
      "MaxFiles": 10
    },
    "Performance": {
      "MaxTransactionsPerBlock": 500,
      "MaxFreeTransactionsPerBlock": 20,
      "MaxFreeTransactionSize": 1024,
      "FeePerExtraByte": 0.00001,
      "BlockCacheSize": 1000,
      "MemoryPoolSize": 50000
    }
  }
}